fastapi_babel/__init__.py
fastapi_babel/core.py
fastapi_babel/exceptions.py
fastapi_babel/helpers.py
fastapi_babel/middleware.py
fastapi_babel/properties.py
fastapi_babel-0.0.9.dist-info/LICENSE
fastapi_babel-0.0.9.dist-info/METADATA
fastapi_babel-0.0.9.dist-info/WHEEL
fastapi_babel-0.0.9.dist-info/top_level.txt
fastapi_babel-0.0.9.dist-info/RECORD
