Metadata-Version: 2.1
Name: fastapi-babel
Version: 0.0.9
Summary: FastAPI-babel is an extenstion for I18n and I10n support in FastAPI, based on babel and pytz.
Home-page: https://github.com/Anbarryprojects/fastapi-babel
Author: Parsa Pourmohammad
Author-email: parsapourmohammad1999@gmail.com
Maintainer: Anbarryprojects
License: MIT
Project-URL: Documentation, https://github.com/Anbarryprojects/fastapi-babel
Project-URL: Source Code, https://github.com/Anbarryprojects/fastapi-babel
Project-URL: Issue Tracker, https://github.com/Anbarryprojects/fastapi-babel/issues/
Classifier: Development Status :: 3 - Alpha
Classifier: Environment :: Web Environment
Classifier: Framework :: FastAPI
Classifier: Intended Audience :: Developers
Classifier: Topic :: Internet :: WWW/HTTP :: Dynamic Content
Classifier: Topic :: Software Development :: Libraries :: Application Frameworks
Classifier: Programming Language :: Python :: 3
Classifier: License :: OSI Approved :: MIT License
Classifier: Operating System :: OS Independent
Requires-Python: >=3.7
License-File: LICENSE
Requires-Dist: fastapi
Requires-Dist: uvicorn
Requires-Dist: babel
